empiricalgalo/__init__.py
empiricalgalo/_version.py
empiricalgalo/abundance_match.py
empiricalgalo/proxy.py
empiricalgalo-0.1.3.dist-info/LICENSE
empiricalgalo-0.1.3.dist-info/METADATA
empiricalgalo-0.1.3.dist-info/WHEEL
empiricalgalo-0.1.3.dist-info/top_level.txt
empiricalgalo-0.1.3.dist-info/RECORD
